pyodk/__init__.py
pyodk/__version__.py
pyodk/client.py
pyodk/errors.py
pyodk/_endpoints/__init__.py
pyodk/_endpoints/auth.py
pyodk/_endpoints/bases.py
pyodk/_endpoints/comments.py
pyodk/_endpoints/entities.py
pyodk/_endpoints/entity_list_properties.py
pyodk/_endpoints/entity_lists.py
pyodk/_endpoints/form_assignments.py
pyodk/_endpoints/form_draft_attachments.py
pyodk/_endpoints/form_drafts.py
pyodk/_endpoints/forms.py
pyodk/_endpoints/project_app_users.py
pyodk/_endpoints/projects.py
pyodk/_endpoints/submission_attachments.py
pyodk/_endpoints/submissions.py
pyodk/_utils/__init__.py
pyodk/_utils/config.py
pyodk/_utils/session.py
pyodk/_utils/utils.py
pyodk/_utils/validators.py
pyodk-1.2.1.dist-info/licenses/LICENSE.md
pyodk-1.2.1.dist-info/WHEEL
pyodk-1.2.1.dist-info/METADATA
pyodk-1.2.1.dist-info/RECORD
