Metadata-Version: 2.4
Name: pyodk
Version: 1.2.1
Summary: The official Python library for ODK 🐍
Author-email: "github.com/getodk" <support@getodk.org>
Requires-Python: >=3.10
License-File: LICENSE.md
Requires-Dist: requests==2.32.3
Requires-Dist: toml==0.10.2
Requires-Dist: pydantic>=2.6.4,<2.9.3
Requires-Dist: ruff==0.7.1 ; extra == "dev"
Requires-Dist: openpyxl==3.1.5 ; extra == "dev"
Requires-Dist: xlwt==1.3.0 ; extra == "dev"
Requires-Dist: mkdocs==1.6.1 ; extra == "docs"
Requires-Dist: mkdocstrings==0.28.3 ; extra == "docs"
Requires-Dist: mkdocstrings-python==1.16.3 ; extra == "docs"
Requires-Dist: mkdocs-jupyter==0.25.1 ; extra == "docs"
Project-URL: Homepage, https://pypi.python.org/pypi/pyodk/
Project-URL: Repository, https://github.com/getodk/pyodk/
Provides-Extra: dev
Provides-Extra: docs
